COPYRIGHT
MANIFEST.in
README.md
informixdb.py
old_datetime.py
setup.py
InformixDB_Knight.egg-info/PKG-INFO
InformixDB_Knight.egg-info/SOURCES.txt
InformixDB_Knight.egg-info/dependency_links.txt
InformixDB_Knight.egg-info/top_level.txt
doc/Makefile
doc/default.css
doc/informixdb.css
doc/manual.txt
ext/_informixdb.c
ext/_informixdb.ec
ext/datetime-compat.h
tests/11-py.conf
tests/dbapi20.py
tests/source_env
tests/test.py
tests/test_for_wsgi.py
tests/testdbapi.py